firstpackage.py
TOPSIS_Vaibhav_101803049-0.0.2.dist-info/LICENSE.txt
TOPSIS_Vaibhav_101803049-0.0.2.dist-info/METADATA
TOPSIS_Vaibhav_101803049-0.0.2.dist-info/WHEEL
TOPSIS_Vaibhav_101803049-0.0.2.dist-info/top_level.txt
TOPSIS_Vaibhav_101803049-0.0.2.dist-info/RECORD
