Metadata-Version: 2.1
Name: TOPSIS-Vaibhav-101803049
Version: 0.0.2
Summary: Example Package
Home-page: UNKNOWN
Author: Vaibhav Allahbadia
Author-email: vallahbadia_be18@thapar.edu
License: UNKNOWN
Platform: UNKNOWN
Classifier: Programming Language :: Python :: 3
Classifier: Programming Language :: Python :: 3.6
Classifier: Programming Language :: Python :: 3.7
Classifier: License :: OSI Approved :: MIT License
Classifier: Operating System :: OS Independent
Requires-Python: >=3.6
